{
  "name": "Freebird",
  "display_name": "Freebird",
  "group_name": "Flight",
  "conversion_groups": [
    "Rarity: Rare",
    "Category: Flight"
  ],
  "boost_lists": [
    [
      "Boosts.Crafted_Freebird_A.Crafted_Freebird_A",
      "Boosts.Attuned_Freebird_A.Attuned_Freebird_A"
    ],
    [
      "Boosts.Crafted_Freebird_B.Crafted_Freebird_B",
      "Boosts.Attuned_Freebird_B.Attuned_Freebird_B"
    ],
    [
      "Boosts.Crafted_Freebird_C.Crafted_Freebird_C",
      "Boosts.Attuned_Freebird_C.Attuned_Freebird_C"
    ]
  ],
  "min_level": 15,
  "max_level": 50,
  "bonuses": [
    {
      "min_boosts": 2,
      "max_boosts": 3,
      "auto_powers": [
        "set_bonus.set_bonus.improved_regeneration_3"
      ],
      "bonus_power": "",
      "requires": "",
      "is_pvp_bonus": false
    },
    {
      "min_boosts": 3,
      "max_boosts": 3,
      "auto_powers": [
        "set_bonus.set_bonus.increased_health_3"
      ],
      "bonus_power": "",
      "requires": "",
      "is_pvp_bonus": false
    }
  ],
  "computed": {
    "boost_type": [
      "Enhance Flying Speed",
      "Enhance Flying Speed",
      "Enhance Flying Speed",
      "Enhance Flying Speed",
      "Enhance Flying Speed",
      "Enhance Flying Speed"
    ],
    "bonuses": [
      [
        [
          "set_bonus.set_bonus.improved_regeneration_3",
          "Moderate Improved Regeneration Bonus"
        ]
      ],
      [
        [
          "set_bonus.set_bonus.increased_health_3",
          "Moderate Increased Health Bonus"
        ]
      ]
    ],
    "globals": {},
    "icons": [
      "e_icon_freebird.png",
      "e_icon_freebird.png",
      "e_icon_freebird.png",
      "e_icon_freebird.png",
      "e_icon_freebird.png",
      "e_icon_freebird.png"
    ],
    "boosts": [
      [
        "Freebird: Endurance",
        "Attuned Freebird: Endurance"
      ],
      [
        "Freebird: Fly",
        "Attuned Freebird: Fly"
      ],
      [
        "Freebird: +Stealth",
        "Attuned Freebird: +Stealth"
      ]
    ],
    "boost_infos": {
      "crafted_freebird_a": {
        "slot_requires": "",
        "ignores_level_differences": true,
        "bonuses_ignore_exemplar": false,
        "combinable": false,
        "tradeable": true,
        "account_bound": false,
        "boostable": true,
        "attuned": false,
        "catalyzes_to": [
          "boosts.attuned_freebird_a.attuned_freebird_a",
          "Freebird: Endurance"
        ],
        "max_level": 50,
        "min_slot_level": 11,
        "min_bonus_level": 8,
        "computed_name": "Freebird: Endurance",
        "aspects": [
          "Endurance"
        ],
        "superior_scales": false,
        "boostset_name": "freebird",
        "global_bonuses": null,
        "is_proc": false,
        "is_unique": false,
        "restricted_ats": null,
        "unique_group": null,
        "only_at_50": false,
        "boost_type": "Enhance Flying Speed",
        "icon": "e_icon_freebird.png"
      },
      "attuned_freebird_a": {
        "slot_requires": "",
        "ignores_level_differences": true,
        "bonuses_ignore_exemplar": false,
        "combinable": false,
        "tradeable": true,
        "account_bound": false,
        "boostable": false,
        "attuned": true,
        "catalyzes_to": null,
        "max_level": 50,
        "min_slot_level": 11,
        "min_bonus_level": 8,
        "computed_name": "Attuned Freebird: Endurance",
        "aspects": [
          "Endurance"
        ],
        "superior_scales": false,
        "boostset_name": "freebird",
        "global_bonuses": null,
        "is_proc": false,
        "is_unique": false,
        "restricted_ats": null,
        "unique_group": null,
        "only_at_50": false,
        "boost_type": "Enhance Flying Speed",
        "icon": "e_icon_freebird.png"
      },
      "crafted_freebird_b": {
        "slot_requires": "",
        "ignores_level_differences": true,
        "bonuses_ignore_exemplar": false,
        "combinable": false,
        "tradeable": true,
        "account_bound": false,
        "boostable": true,
        "attuned": false,
        "catalyzes_to": [
          "boosts.attuned_freebird_b.attuned_freebird_b",
          "Freebird: Fly"
        ],
        "max_level": 50,
        "min_slot_level": 11,
        "min_bonus_level": 8,
        "computed_name": "Freebird: Fly",
        "aspects": [
          "Fly"
        ],
        "superior_scales": false,
        "boostset_name": "freebird",
        "global_bonuses": null,
        "is_proc": false,
        "is_unique": false,
        "restricted_ats": null,
        "unique_group": null,
        "only_at_50": false,
        "boost_type": "Enhance Flying Speed",
        "icon": "e_icon_freebird.png"
      },
      "attuned_freebird_b": {
        "slot_requires": "",
        "ignores_level_differences": true,
        "bonuses_ignore_exemplar": false,
        "combinable": false,
        "tradeable": true,
        "account_bound": false,
        "boostable": false,
        "attuned": true,
        "catalyzes_to": null,
        "max_level": 50,
        "min_slot_level": 11,
        "min_bonus_level": 8,
        "computed_name": "Attuned Freebird: Fly",
        "aspects": [
          "Fly"
        ],
        "superior_scales": false,
        "boostset_name": "freebird",
        "global_bonuses": null,
        "is_proc": false,
        "is_unique": false,
        "restricted_ats": null,
        "unique_group": null,
        "only_at_50": false,
        "boost_type": "Enhance Flying Speed",
        "icon": "e_icon_freebird.png"
      },
      "crafted_freebird_c": {
        "slot_requires": "(BoostsSlotted>Attuned_Celerity_C <= 0) && (BoostsSlotted>Attuned_Freebird_C <= 0) && (BoostsSlotted>Attuned_TimeSpace_Manipulation_C <= 0) && (BoostsSlotted>Attuned_Unbounded_Leap_C <= 0) && (BoostsSlotted>Crafted_Celerity_C <= 0) && (BoostsSlotted>Crafted_Freebird_C <= 0) && (BoostsSlotted>Crafted_TimeSpace_Manipulation_C <= 0) && (BoostsSlotted>Crafted_Unbounded_Leap_C <= 0)",
        "ignores_level_differences": true,
        "bonuses_ignore_exemplar": false,
        "combinable": false,
        "tradeable": true,
        "account_bound": false,
        "boostable": false,
        "attuned": false,
        "catalyzes_to": [
          "boosts.attuned_freebird_c.attuned_freebird_c",
          "Freebird: Stealth"
        ],
        "max_level": 50,
        "min_slot_level": 11,
        "min_bonus_level": 8,
        "computed_name": "Freebird: +Stealth",
        "aspects": [],
        "superior_scales": false,
        "boostset_name": "freebird",
        "global_bonuses": null,
        "is_proc": true,
        "is_unique": false,
        "restricted_ats": [],
        "unique_group": [
          "attuned_celerity_c",
          "attuned_freebird_c",
          "attuned_timespace_manipulation_c",
          "attuned_unbounded_leap_c",
          "crafted_celerity_c",
          "crafted_freebird_c",
          "crafted_timespace_manipulation_c",
          "crafted_unbounded_leap_c"
        ],
        "only_at_50": false,
        "boost_type": "Enhance Flying Speed",
        "icon": "e_icon_freebird.png"
      },
      "attuned_freebird_c": {
        "slot_requires": "(BoostsSlotted>Attuned_Celerity_C <= 0) && (BoostsSlotted>Attuned_Freebird_C <= 0) && (BoostsSlotted>Attuned_TimeSpace_Manipulation_C <= 0) && (BoostsSlotted>Attuned_Unbounded_Leap_C <= 0) && (BoostsSlotted>Crafted_Celerity_C <= 0) && (BoostsSlotted>Crafted_Freebird_C <= 0) && (BoostsSlotted>Crafted_TimeSpace_Manipulation_C <= 0) && (BoostsSlotted>Crafted_Unbounded_Leap_C <= 0)",
        "ignores_level_differences": true,
        "bonuses_ignore_exemplar": false,
        "combinable": false,
        "tradeable": true,
        "account_bound": false,
        "boostable": false,
        "attuned": true,
        "catalyzes_to": null,
        "max_level": 50,
        "min_slot_level": 11,
        "min_bonus_level": 8,
        "computed_name": "Attuned Freebird: +Stealth",
        "aspects": [],
        "superior_scales": false,
        "boostset_name": "freebird",
        "global_bonuses": null,
        "is_proc": true,
        "is_unique": false,
        "restricted_ats": [],
        "unique_group": [
          "attuned_celerity_c",
          "attuned_freebird_c",
          "attuned_timespace_manipulation_c",
          "attuned_unbounded_leap_c",
          "crafted_celerity_c",
          "crafted_freebird_c",
          "crafted_timespace_manipulation_c",
          "crafted_unbounded_leap_c"
        ],
        "only_at_50": false,
        "boost_type": "Enhance Flying Speed",
        "icon": "e_icon_freebird.png"
      }
    }
  }
}
